dict_to_csv/__init__.py
dict_to_csv-0.1.4.dist-info/DESCRIPTION.rst
dict_to_csv-0.1.4.dist-info/METADATA
dict_to_csv-0.1.4.dist-info/RECORD
dict_to_csv-0.1.4.dist-info/WHEEL
dict_to_csv-0.1.4.dist-info/metadata.json
dict_to_csv-0.1.4.dist-info/top_level.txt
