Metadata-Version: 2.0
Name: dict-to-csv
Version: 0.1.4
Summary: Transform nested Python dictionaries to CSV lines
Home-page: https://github.com/thulio/dict-to-csv
Author: Thúlio Costa
Author-email: contact@thul.io
License: MIT
Platform: UNKNOWN
Classifier: License :: OSI Approved :: MIT License
Classifier: Topic :: Software Development :: Libraries
Classifier: Programming Language :: Python :: 2.7
Classifier: Programming Language :: Python :: 3.4
Classifier: Programming Language :: Python :: 3.5
Classifier: Programming Language :: Python :: 3.6
Classifier: Programming Language :: Python :: Implementation :: PyPy
Requires-Dist: dotmap (==1.2.17)
Requires-Dist: typing (==3.5.3.0)
